{
  "name": "Xender",
  "Description":"upgraded ver of seo,shoots super long lancer laser, reload slow",
  "type":"flying",
  "flying": true,
  "speed": 5,
  "drag": 1,
  "armor": 2,
  "engineOffset": 8,
  "targetAir": true,
  "hitSize": 2,
  "health": 1000,
  "accel": 1,
  "weapons": [
    {
      "name": "long-lancer",
      "reload": 120,
      "top": true,
      "mirror": false,
      "x": 0,
      "y": -2,
      "shootY": 2,
      "recoil": 1.5,
      "shake": 0.5,
      "rotateSpeed": 1,
      "rotate": true,
      "shots": 1,
      "shootSound": "lasershoot",
      "shootCone": 45,
      "bullet": {
        "type": "LaserBulletType",
        "damage": 120,
        "frontColor": "42d4f5",
               "backColor": "5366a6",
        "length":400,
        "width":5
      }
    }
  ]
}
  